knesset_data/__init__.py
knesset_data/exceptions.py
knesset_data/dataservice/__init__.py
knesset_data/dataservice/base.py
knesset_data/dataservice/bill_history_initiator.py
knesset_data/dataservice/bill_initiator.py
knesset_data/dataservice/bill_name.py
knesset_data/dataservice/bill_split.py
knesset_data/dataservice/bill_union.py
knesset_data/dataservice/bills.py
knesset_data/dataservice/committees.py
knesset_data/dataservice/constants.py
knesset_data/dataservice/document_bill.py
knesset_data/dataservice/exceptions.py
knesset_data/dataservice/laws.py
knesset_data/dataservice/members.py
knesset_data/dataservice/mocks.py
knesset_data/dataservice/persons.py
knesset_data/dataservice/utils.py
knesset_data/dataservice/votes.py
knesset_data/dataservice/monitor/__init__.py
knesset_data/dataservice/monitor/metadata/__init__.py
knesset_data/dataservice/monitor/metadata/initial.py
knesset_data/dataservice/monitor/metadata/periodic.py
knesset_data/dataservice/tests/__init__.py
knesset_data/dataservice/tests/test_members.py
knesset_data/dataservice/tests/base/__init__.py
knesset_data/dataservice/tests/base/test_exceptions.py
knesset_data/dataservice/tests/bills/__init__.py
knesset_data/dataservice/tests/bills/test_bills.py
knesset_data/dataservice/tests/bills/test_integration_bill_related.py
knesset_data/dataservice/tests/committees/__init__.py
knesset_data/dataservice/tests/committees/test_committees.py
knesset_data/dataservice/tests/committees/test_meetings.py
knesset_data/dataservice/tests/laws/__init__.py
knesset_data/dataservice/tests/laws/test_laws.py
knesset_data/dataservice/tests/votes/__init__.py
knesset_data/dataservice/tests/votes/test_vote_members.py
knesset_data/dataservice/tests/votes/test_votes.py
knesset_data/html_scrapers/__init__.py
knesset_data/html_scrapers/mocks.py
knesset_data/html_scrapers/plenum.py
knesset_data/html_scrapers/votes.py
knesset_data/html_scrapers/tests/__init__.py
knesset_data/html_scrapers/tests/test_html_vote.py
knesset_data-2.1.5.dist-info/METADATA
knesset_data-2.1.5.dist-info/WHEEL
knesset_data-2.1.5.dist-info/top_level.txt
knesset_data-2.1.5.dist-info/RECORD
