Metadata-Version: 2.1
Name: knesset-data
Version: 2.1.5
Summary: API for access to available Israeli Parliament (Knesset) data
Home-page: https://github.com/hasadna/knesset-data-python
Author: Ori Hoch
Author-email: ori@uumpa.com
License: GPLv3
Platform: UNKNOWN
Requires-Dist: beautifulsoup4
Requires-Dist: pyslet
Requires-Dist: requests
Requires-Dist: simplejson
Requires-Dist: pyth
Requires-Dist: python-hebrew-numbers
Requires-Dist: cached-property
Requires-Dist: six
Provides-Extra: develop
Requires-Dist: tox ; extra == 'develop'
